engrate_sdk/__init__.py
engrate_sdk/py.typed
engrate_sdk/core/registry.py
engrate_sdk/http/client.py
engrate_sdk/http/server.py
engrate_sdk/types/base.py
engrate_sdk/types/exceptions.py
engrate_sdk/types/plugins.py
engrate_sdk/utils/env.py
engrate_sdk/utils/log.py
engrate_sdk/utils/mock_registrar.py
engrate_sdk/utils/uuid.py
engrate_sdk-0.0.24.dist-info/METADATA
engrate_sdk-0.0.24.dist-info/WHEEL
engrate_sdk-0.0.24.dist-info/RECORD
